{
  "sat_0": {
    "sample_count": 169493,
    "label_distribution": {
      "0": 56209,
      "1": 2643,
      "2": 8456,
      "3": 11158,
      "4": 10481,
      "5": 75199,
      "6": 5076,
      "7": 271
    }
  },
  "sat_1": {
    "sample_count": 98910,
    "label_distribution": {
      "0": 91373,
      "1": 11,
      "2": 497,
      "3": 2194,
      "4": 1015,
      "5": 1102,
      "6": 2397,
      "7": 321
    }
  },
  "sat_2": {
    "sample_count": 270211,
    "label_distribution": {
      "0": 137951,
      "1": 47890,
      "2": 391,
      "3": 218,
      "4": 456,
      "5": 5181,
      "6": 17199,
      "7": 60925
    }
  },
  "sat_3": {
    "sample_count": 86623,
    "label_distribution": {
      "0": 650,
      "1": 64,
      "2": 3037,
      "3": 45,
      "4": 2004,
      "5": 35,
      "6": 131,
      "7": 80657
    }
  },
  "sat_4": {
    "sample_count": 6121,
    "label_distribution": {
      "0": 1372,
      "2": 59,
      "3": 1,
      "4": 43,
      "5": 444,
      "6": 4168,
      "7": 34
    }
  },
  "sat_5": {
    "sample_count": 51398,
    "label_distribution": {
      "0": 83,
      "1": 34353,
      "2": 120,
      "3": 99,
      "4": 16105,
      "5": 2,
      "6": 1,
      "7": 635
    }
  },
  "sat_6": {
    "sample_count": 106567,
    "label_distribution": {
      "0": 390,
      "1": 740,
      "2": 48352,
      "3": 26326,
      "4": 940,
      "5": 20873,
      "6": 8716,
      "7": 230
    }
  },
  "sat_7": {
    "sample_count": 53486,
    "label_distribution": {
      "0": 3495,
      "1": 25,
      "2": 45,
      "3": 13791,
      "4": 38,
      "5": 2450,
      "6": 16901,
      "7": 16741
    }
  },
  "sat_8": {
    "sample_count": 130234,
    "label_distribution": {
      "0": 44570,
      "1": 2381,
      "2": 11385,
      "3": 31445,
      "4": 18077,
      "5": 529,
      "6": 21846,
      "7": 1
    }
  },
  "sat_9": {
    "sample_count": 81253,
    "label_distribution": {
      "0": 3290,
      "1": 12,
      "2": 73820,
      "3": 305,
      "4": 4,
      "5": 264,
      "7": 3558
    }
  },
  "sat_10": {
    "sample_count": 191752,
    "label_distribution": {
      "0": 54803,
      "1": 3639,
      "2": 1185,
      "3": 265,
      "4": 63043,
      "5": 747,
      "6": 67829,
      "7": 241
    }
  },
  "sat_11": {
    "sample_count": 27342,
    "label_distribution": {
      "0": 12929,
      "1": 799,
      "2": 2,
      "3": 67,
      "4": 5000,
      "5": 2717,
      "6": 4689,
      "7": 1139
    }
  }
}